dssuite/__init__.py
dssuite/metrics.py
ds_suite-1.0.7.dist-info/LICENSE.txt
ds_suite-1.0.7.dist-info/METADATA
ds_suite-1.0.7.dist-info/WHEEL
ds_suite-1.0.7.dist-info/top_level.txt
ds_suite-1.0.7.dist-info/RECORD
