Metadata-Version: 2.1
Name: ds-suite
Version: 1.0.7
Summary: A brute-force based way of fiding the best ratio for your data. Focused on Tree models.
Home-page: https://github.com/danielcavalli/ds-suite
Author: Daniel Cavalli
Author-email: daniel@cavalli.dev
License: UNKNOWN
Platform: UNKNOWN
Classifier: Programming Language :: Python :: 3
Classifier: Programming Language :: Python :: 3.7
Classifier: License :: OSI Approved :: MIT License
Classifier: Operating System :: OS Independent
Requires-Dist: awswrangler
Requires-Dist: scikit-learn
